{
  "fingerprint": "320DD86E1E256275B28F89D729CEADC9260F0067",
  "label": "Francesco Namuri",
  "sources": [
    {
      "type": "hkps",
      "uri": "hkps://keyring.debian.org:443"
    },
    {
      "type": "url",
      "uri": "https://db.debian.org/fetchkey.cgi?fingerprint=320DD86E1E256275B28F89D729CEADC9260F0067"
    }
  ],
  "refs": [
    {
      "date": "2025-08-24",
      "comment": "Listed in Debian Developers Database",
      "url": "https://db.debian.org/search.cgi",
      "type": "role"
    }
  ],
  "tags": [
    "debian-dev"
  ]
}
