{
  "fingerprint": "3A0BEE9EEE0E1B7ECC6424E0C03242A988D4B7DF",
  "label": "Jose Parrella",
  "sources": [
    {
      "type": "hkps",
      "uri": "hkps://keyring.debian.org:443"
    },
    {
      "type": "url",
      "uri": "https://db.debian.org/fetchkey.cgi?fingerprint=3A0BEE9EEE0E1B7ECC6424E0C03242A988D4B7DF"
    }
  ],
  "refs": [
    {
      "date": "2025-08-24",
      "comment": "Listed in Debian Developers Database",
      "url": "https://db.debian.org/search.cgi",
      "type": "role"
    }
  ],
  "tags": [
    "debian-dev"
  ]
}
