{
  "fingerprint": "F00F67C10AC612F5418B01975098021C70518078",
  "label": "Alan Woodland",
  "sources": [
    {
      "type": "hkps",
      "uri": "hkps://keyring.debian.org:443"
    },
    {
      "type": "url",
      "uri": "https://db.debian.org/fetchkey.cgi?fingerprint=F00F67C10AC612F5418B01975098021C70518078"
    }
  ],
  "refs": [
    {
      "date": "2025-08-24",
      "comment": "Listed in Debian Developers Database",
      "url": "https://db.debian.org/search.cgi",
      "type": "role"
    }
  ],
  "tags": [
    "debian-dev"
  ]
}
